LICENSE
README.md
setup.cfg
setup.py
aiohelvar/__init__.py
aiohelvar/config.py
aiohelvar/devices.py
aiohelvar/exceptions.py
aiohelvar/groups.py
aiohelvar/lib.py
aiohelvar/router.py
aiohelvar/scenes.py
aiohelvar/static.py
aiohelvar.egg-info/PKG-INFO
aiohelvar.egg-info/SOURCES.txt
aiohelvar.egg-info/dependency_links.txt
aiohelvar.egg-info/top_level.txt
aiohelvar/parser/__init__.py
aiohelvar/parser/address.py
aiohelvar/parser/command.py
aiohelvar/parser/command_parameter.py
aiohelvar/parser/command_type.py
aiohelvar/parser/parser.py
aiohelvar/parser/test_parser.py