Metadata-Version: 2.1
Name: aiohelvar
Version: 0.9.2
Summary: Async HelvarNet communication and control library.
Home-page: https://github.com/tomplayford/aiohelvar
Author: Tom Playford
License: Apache 2.0
Download-URL: https://github.com/tomplayford/aiohelvar/archive/refs/tags/V0.9.1.tar.gz
Project-URL: Bug Tracker, https://github.com/tomplayford/aiohelvar/issues
Platform: UNKNOWN
Classifier: Programming Language :: Python :: 3
Classifier: Operating System :: OS Independent
Requires-Python: >=3.8
License-File: LICENSE
